git_diff_helper/__init__.py
git_diff_helper/__main__.py
git_diff_helper/core.py
git_diff_helper-0.1.7.dist-info/LICENSE
git_diff_helper-0.1.7.dist-info/METADATA
git_diff_helper-0.1.7.dist-info/WHEEL
git_diff_helper-0.1.7.dist-info/entry_points.txt
git_diff_helper-0.1.7.dist-info/top_level.txt
git_diff_helper-0.1.7.dist-info/RECORD
