Metadata-Version: 2.1
Name: git-diff-helper
Version: 0.1.7
Summary: A tool for generating Git diff reports optimized for AI code review
Home-page: https://github.com/mlusas/git-diff-helper
Author: Mitch Lusas
Author-email: git@mitchlusas.com
Classifier: Development Status :: 3 - Alpha
Classifier: Intended Audience :: Developers
Classifier: Topic :: Software Development :: Version Control :: Git
Classifier: License :: OSI Approved :: MIT License
Classifier: Programming Language :: Python :: 3
Classifier: Programming Language :: Python :: 3.6
Classifier: Programming Language :: Python :: 3.7
Classifier: Programming Language :: Python :: 3.8
Classifier: Programming Language :: Python :: 3.9
Requires-Python: >=3.6
License-File: LICENSE
Requires-Dist: typing-extensions>=4.0.0
